{
  "project_info": {
    "project_number": "973404555520",
    "project_id": "versioncontrol-f0149",
    "storage_bucket": "versioncontrol-f0149.appspot.com"
  },
  "client": [
    {
      "client_info": {
        "mobilesdk_app_id": "1:973404555520:android:ee615ee666cc505a718be5",
        "android_client_info": {
          "package_name": "com.appyhigh.vc"
        }
      },
      "oauth_client": [
        {
          "client_id": "973404555520-70i3re75v7h8553ak6iv39gjf9lq61o4.apps.googleusercontent.com",
          "client_type": 3
        }
      ],
      "api_key": [
        {
          "current_key": "AIzaSyCCrzjAjZ4SN405alLax3GnFQLkxXOU1jg"
        }
      ],
      "services": {
        "appinvite_service": {
          "other_platform_oauth_client": [
            {
              "client_id": "973404555520-70i3re75v7h8553ak6iv39gjf9lq61o4.apps.googleusercontent.com",
              "client_type": 3
            }
          ]
        }
      }
    }
  ],
  "configuration_version": "1"
}